importhook/__init__.py
importhook/finder.py
importhook/loader.py
importhook/logger.py
importhook/meta_paths.py
importhook/registry.py
importhook/utils.py
importhook/tests/test_meta_paths.py
importhook-1.0.9.dist-info/LICENSE
importhook-1.0.9.dist-info/METADATA
importhook-1.0.9.dist-info/WHEEL
importhook-1.0.9.dist-info/top_level.txt
importhook-1.0.9.dist-info/RECORD
