Metadata-Version: 2.1
Name: importhook
Version: 1.0.9
Summary: Execute code when certain modules are imported
Home-page: https://github.com/brettlangdon/importhook
Author: Brett Langdon
Author-email: me@brett.is
License: MIT
Platform: any
Classifier: Development Status :: 5 - Production/Stable
Classifier: Intended Audience :: Developers
Classifier: License :: OSI Approved :: MIT License
Classifier: Operating System :: OS Independent
Classifier: Programming Language :: Python :: 3
Classifier: Programming Language :: Python
Requires-Python: >3.3
